odoo/addons/l10n_us_mis_financial_report/README.rst
odoo/addons/l10n_us_mis_financial_report/__init__.py
odoo/addons/l10n_us_mis_financial_report/__manifest__.py
odoo/addons/l10n_us_mis_financial_report/data/mis_report.xml
odoo/addons/l10n_us_mis_financial_report/data/mis_report_kpi.xml
odoo/addons/l10n_us_mis_financial_report/data/mis_report_style.xml
odoo/addons/l10n_us_mis_financial_report/data/mis_report_subreport.xml
odoo/addons/l10n_us_mis_financial_report/i18n/es.po
odoo/addons/l10n_us_mis_financial_report/i18n/l10n_us_mis_financial_report.pot
odoo/addons/l10n_us_mis_financial_report/readme/CONTRIBUTORS.md
odoo/addons/l10n_us_mis_financial_report/readme/DESCRIPTION.md
odoo/addons/l10n_us_mis_financial_report/readme/USAGE.md
odoo/addons/l10n_us_mis_financial_report/readme/newsfragments/.gitkeep
odoo/addons/l10n_us_mis_financial_report/static/description/icon.png
odoo/addons/l10n_us_mis_financial_report/static/description/index.html
odoo_addon_l10n_us_mis_financial_report-18.0.1.0.0.2.dist-info/METADATA
odoo_addon_l10n_us_mis_financial_report-18.0.1.0.0.2.dist-info/WHEEL
odoo_addon_l10n_us_mis_financial_report-18.0.1.0.0.2.dist-info/top_level.txt
odoo_addon_l10n_us_mis_financial_report-18.0.1.0.0.2.dist-info/RECORD
