Metadata-Version: 2.1
Name: odoo-addon-l10n_us_mis_financial_report
Version: 18.0.1.0.0.2
Requires-Python: >=3.10
Requires-Dist: odoo-addon-mis_template_financial_report==18.0.*
Requires-Dist: odoo==18.0.*
Summary: Profit & Loss (US) / Balance sheet (US) MIS templates
Home-page: https://github.com/OCA/l10n-usa
License: AGPL-3
Author: Binhex,Odoo Community Association (OCA)
Author-email: support@odoo-community.org
Classifier: Programming Language :: Python
Classifier: Framework :: Odoo
Classifier: Framework :: Odoo :: 18.0
Classifier: License :: OSI Approved :: GNU Affero General Public License v3
